scottypy/__init__.py
scottypy/__version__.py
scottypy/app.py
scottypy/beam.py
scottypy/exc.py
scottypy/file.py
scottypy/scotty.py
scottypy/types.py
scottypy/utils.py
scottypy-0.27.0.dist-info/METADATA
scottypy-0.27.0.dist-info/WHEEL
scottypy-0.27.0.dist-info/entry_points.txt
scottypy-0.27.0.dist-info/top_level.txt
scottypy-0.27.0.dist-info/RECORD
