Metadata-Version: 2.1
Name: scottypy
Version: 0.27.0
Summary: A library for beaming up files to Scotty
Home-page: https://github.com/getslash/scottypy
Author: Roey Darwish Dror
Author-email: roey.ghost@gmail.com
License: BSD
Platform: UNKNOWN
Classifier: Programming Language :: Python :: 3.5
Classifier: Programming Language :: Python :: 3.6
Classifier: Programming Language :: Python :: 3.7
Classifier: Programming Language :: Python :: 3.8
Requires-Dist: capacity
Requires-Dist: click
Requires-Dist: emport
Requires-Dist: python-dateutil
Requires-Dist: requests
Requires-Dist: pact
